wclone/__init__.py
wclone/__main__.py
wclone/app.py
wclone-1.0.2.dist-info/METADATA
wclone-1.0.2.dist-info/WHEEL
wclone-1.0.2.dist-info/entry_points.txt
wclone-1.0.2.dist-info/top_level.txt
wclone-1.0.2.dist-info/RECORD
