Metadata-Version: 2.1
Name: wclone
Version: 1.0.2
Summary: Basic website cloner written in Python
Home-page: https://github.com/ZKAW/website-cloner
Author: ZKAW
Maintainer: Smartwa
Maintainer-email: smartwacaleb@gmail.com
License: MIT License
Project-URL: Bug Report, https://github.com/ZKAW/website-cloner/issues/new
Classifier: License :: OSI Approved :: MIT License
Classifier: Intended Audience :: Developers
Classifier: Topic :: Software Development :: Libraries :: Python Modules
Classifier: Programming Language :: Python :: 3.8
Classifier: Programming Language :: Python :: 3.9
Classifier: Programming Language :: Python :: 3.10
Classifier: Programming Language :: Python :: 3.11
Requires-Python: >=3.8
Requires-Dist: bs4
Requires-Dist: requests
Requires-Dist: cloudscraper (==1.2.69)
